{
  "manifestVersion": "3.2",
  "proxies": [
    {
      "address": "0x327B5Cc65f23494eCD1774B3Fb7C9d1Ab90cb1fd",
      "txHash": "0xf1f2c600b17caffbb3692246fd6b51ebb2c2dacd249c12673377c53c6813785d",
      "kind": "uups"
    }
  ],
  "impls": {
    "1a5edf71d772e46af6a64d6b364060603dad63a176ecbdaaa3626ca1727c8eab": {
      "address": "0xa4cE61ad0143412d47907071F08C2755609c62a1",
      "txHash": "0x4ab4298757722c28dd3ecabdb2260df16169ab9f3a63435b1d286bf00ac480ed",
      "layout": {
        "solcVersion": "0.8.17",
        "storage": [
          {
            "label": "_initialized",
            "offset": 0,
            "slot": "0",
            "type": "t_uint8",
            "contract": "Initializable",
            "src": "@openzeppelin/contracts-upgradeable/proxy/utils/Initializable.sol:62",
            "retypedFrom": "bool"
          },
          {
            "label": "_initializing",
            "offset": 1,
            "slot": "0",
            "type": "t_bool",
            "contract": "Initializable",
            "src": "@openzeppelin/contracts-upgradeable/proxy/utils/Initializable.sol:67"
          },
          {
            "label": "__gap",
            "offset": 0,
            "slot": "1",
            "type": "t_array(t_uint256)50_storage",
            "contract": "ERC1967UpgradeUpgradeable",
            "src": "@openzeppelin/contracts-upgradeable/proxy/ERC1967/ERC1967UpgradeUpgradeable.sol:211"
          },
          {
            "label": "__gap",
            "offset": 0,
            "slot": "51",
            "type": "t_array(t_uint256)50_storage",
            "contract": "UUPSUpgradeable",
            "src": "@openzeppelin/contracts-upgradeable/proxy/utils/UUPSUpgradeable.sol:107"
          },
          {
            "label": "__gap",
            "offset": 0,
            "slot": "101",
            "type": "t_array(t_uint256)50_storage",
            "contract": "ContextUpgradeable",
            "src": "@openzeppelin/contracts-upgradeable/utils/ContextUpgradeable.sol:36"
          },
          {
            "label": "_owner",
            "offset": 0,
            "slot": "151",
            "type": "t_address",
            "contract": "OwnableUpgradeable",
            "src": "@openzeppelin/contracts-upgradeable/access/OwnableUpgradeable.sol:22"
          },
          {
            "label": "__gap",
            "offset": 0,
            "slot": "152",
            "type": "t_array(t_uint256)49_storage",
            "contract": "OwnableUpgradeable",
            "src": "@openzeppelin/contracts-upgradeable/access/OwnableUpgradeable.sol:94"
          },
          {
            "label": "PartyDetails",
            "offset": 0,
            "slot": "201",
            "type": "t_mapping(t_uint256,t_struct(Agreement)1380_storage)",
            "contract": "AgreementContract",
            "src": "contracts/Agreement.sol:29"
          }
        ],
        "types": {
          "t_address": {
            "label": "address",
            "numberOfBytes": "20"
          },
          "t_array(t_uint256)49_storage": {
            "label": "uint256[49]",
            "numberOfBytes": "1568"
          },
          "t_array(t_uint256)50_storage": {
            "label": "uint256[50]",
            "numberOfBytes": "1600"
          },
          "t_bool": {
            "label": "bool",
            "numberOfBytes": "1"
          },
          "t_mapping(t_uint256,t_struct(Agreement)1380_storage)": {
            "label": "mapping(uint256 => struct AgreementContract.Agreement)",
            "numberOfBytes": "32"
          },
          "t_string_storage": {
            "label": "string",
            "numberOfBytes": "32"
          },
          "t_struct(Agreement)1380_storage": {
            "label": "struct AgreementContract.Agreement",
            "members": [
              {
                "label": "Terms",
                "type": "t_string_storage",
                "offset": 0,
                "slot": "0"
              },
              {
                "label": "Date",
                "type": "t_string_storage",
                "offset": 0,
                "slot": "1"
              },
              {
                "label": "party1",
                "type": "t_string_storage",
                "offset": 0,
                "slot": "2"
              },
              {
                "label": "Sign1",
                "type": "t_bool",
                "offset": 0,
                "slot": "3"
              },
              {
                "label": "party2",
                "type": "t_string_storage",
                "offset": 0,
                "slot": "4"
              },
              {
                "label": "Sign2",
                "type": "t_bool",
                "offset": 0,
                "slot": "5"
              }
            ],
            "numberOfBytes": "192"
          },
          "t_uint256": {
            "label": "uint256",
            "numberOfBytes": "32"
          },
          "t_uint8": {
            "label": "uint8",
            "numberOfBytes": "1"
          }
        }
      }
    },
    "910fe6683537503351360ce1eb8dd5a69d1aa924052064209004b45e254000c0": {
      "address": "0x4545Bc84b8894E0b31195773a0DAAb1BBb751D56",
      "txHash": "0x3a2b5276288c905a3feff7c330a8259daee2cad4f279eb1da01405e4156524ee",
      "layout": {
        "solcVersion": "0.8.17",
        "storage": [
          {
            "label": "_initialized",
            "offset": 0,
            "slot": "0",
            "type": "t_uint8",
            "contract": "Initializable",
            "src": "@openzeppelin/contracts-upgradeable/proxy/utils/Initializable.sol:62",
            "retypedFrom": "bool"
          },
          {
            "label": "_initializing",
            "offset": 1,
            "slot": "0",
            "type": "t_bool",
            "contract": "Initializable",
            "src": "@openzeppelin/contracts-upgradeable/proxy/utils/Initializable.sol:67"
          },
          {
            "label": "__gap",
            "offset": 0,
            "slot": "1",
            "type": "t_array(t_uint256)50_storage",
            "contract": "ERC1967UpgradeUpgradeable",
            "src": "@openzeppelin/contracts-upgradeable/proxy/ERC1967/ERC1967UpgradeUpgradeable.sol:211"
          },
          {
            "label": "__gap",
            "offset": 0,
            "slot": "51",
            "type": "t_array(t_uint256)50_storage",
            "contract": "UUPSUpgradeable",
            "src": "@openzeppelin/contracts-upgradeable/proxy/utils/UUPSUpgradeable.sol:107"
          },
          {
            "label": "__gap",
            "offset": 0,
            "slot": "101",
            "type": "t_array(t_uint256)50_storage",
            "contract": "ContextUpgradeable",
            "src": "@openzeppelin/contracts-upgradeable/utils/ContextUpgradeable.sol:36"
          },
          {
            "label": "_owner",
            "offset": 0,
            "slot": "151",
            "type": "t_address",
            "contract": "OwnableUpgradeable",
            "src": "@openzeppelin/contracts-upgradeable/access/OwnableUpgradeable.sol:22"
          },
          {
            "label": "__gap",
            "offset": 0,
            "slot": "152",
            "type": "t_array(t_uint256)49_storage",
            "contract": "OwnableUpgradeable",
            "src": "@openzeppelin/contracts-upgradeable/access/OwnableUpgradeable.sol:94"
          },
          {
            "label": "PartyDetails",
            "offset": 0,
            "slot": "201",
            "type": "t_mapping(t_uint256,t_struct(Agreement)1380_storage)",
            "contract": "AgreementContract",
            "src": "contracts/Agreement.sol:29"
          },
          {
            "label": "_trustedForwarder",
            "offset": 0,
            "slot": "202",
            "type": "t_address",
            "contract": "ERC2771Recipient",
            "src": "@opengsn/contracts/src/ERC2771Recipient.sol:21"
          }
        ],
        "types": {
          "t_address": {
            "label": "address",
            "numberOfBytes": "20"
          },
          "t_array(t_uint256)49_storage": {
            "label": "uint256[49]",
            "numberOfBytes": "1568"
          },
          "t_array(t_uint256)50_storage": {
            "label": "uint256[50]",
            "numberOfBytes": "1600"
          },
          "t_bool": {
            "label": "bool",
            "numberOfBytes": "1"
          },
          "t_mapping(t_uint256,t_struct(Agreement)1380_storage)": {
            "label": "mapping(uint256 => struct AgreementContract.Agreement)",
            "numberOfBytes": "32"
          },
          "t_string_storage": {
            "label": "string",
            "numberOfBytes": "32"
          },
          "t_struct(Agreement)1380_storage": {
            "label": "struct AgreementContract.Agreement",
            "members": [
              {
                "label": "Terms",
                "type": "t_string_storage",
                "offset": 0,
                "slot": "0"
              },
              {
                "label": "Date",
                "type": "t_string_storage",
                "offset": 0,
                "slot": "1"
              },
              {
                "label": "party1",
                "type": "t_string_storage",
                "offset": 0,
                "slot": "2"
              },
              {
                "label": "Sign1",
                "type": "t_bool",
                "offset": 0,
                "slot": "3"
              },
              {
                "label": "party2",
                "type": "t_string_storage",
                "offset": 0,
                "slot": "4"
              },
              {
                "label": "Sign2",
                "type": "t_bool",
                "offset": 0,
                "slot": "5"
              }
            ],
            "numberOfBytes": "192"
          },
          "t_uint256": {
            "label": "uint256",
            "numberOfBytes": "32"
          },
          "t_uint8": {
            "label": "uint8",
            "numberOfBytes": "1"
          }
        }
      }
    }
  }
}
